Metadata-Version: 2.1
Name: ptprint
Version: 1.0.0
Summary: Pretty Terminal print library
Home-page: UNKNOWN
Author: Prepakis Georgios
Author-email: prepakis.geo@gmail.com
License: MIT
Keywords: prettyprint
Platform: UNKNOWN
Classifier: Development Status :: 5 - Production/Stable
Classifier: Intended Audience :: Education
Classifier: Operating System :: Microsoft :: Windows :: Windows 10
Classifier: License :: OSI Approved :: MIT License
Classifier: Programming Language :: Python :: 3
License-File: LICENSE
